aiq/__init__.py
nat/agent/__init__.py
nat/agent/base.py
nat/agent/dual_node.py
nat/agent/register.py
nat/agent/prompt_optimizer/__init__.py
nat/agent/prompt_optimizer/prompt.py
nat/agent/prompt_optimizer/register.py
nat/agent/react_agent/__init__.py
nat/agent/react_agent/agent.py
nat/agent/react_agent/output_parser.py
nat/agent/react_agent/prompt.py
nat/agent/react_agent/register.py
nat/agent/reasoning_agent/__init__.py
nat/agent/reasoning_agent/reasoning_agent.py
nat/agent/rewoo_agent/__init__.py
nat/agent/rewoo_agent/agent.py
nat/agent/rewoo_agent/prompt.py
nat/agent/rewoo_agent/register.py
nat/agent/tool_calling_agent/__init__.py
nat/agent/tool_calling_agent/agent.py
nat/agent/tool_calling_agent/register.py
nat/authentication/__init__.py
nat/authentication/interfaces.py
nat/authentication/register.py
nat/authentication/api_key/__init__.py
nat/authentication/api_key/api_key_auth_provider.py
nat/authentication/api_key/api_key_auth_provider_config.py
nat/authentication/api_key/register.py
nat/authentication/credential_validator/__init__.py
nat/authentication/credential_validator/bearer_token_validator.py
nat/authentication/exceptions/__init__.py
nat/authentication/exceptions/api_key_exceptions.py
nat/authentication/http_basic_auth/__init__.py
nat/authentication/http_basic_auth/http_basic_auth_provider.py
nat/authentication/http_basic_auth/register.py
nat/authentication/oauth2/__init__.py
nat/authentication/oauth2/oauth2_auth_code_flow_provider.py
nat/authentication/oauth2/oauth2_auth_code_flow_provider_config.py
nat/authentication/oauth2/oauth2_resource_server_config.py
nat/authentication/oauth2/register.py
nat/builder/__init__.py
nat/builder/builder.py
nat/builder/component_utils.py
nat/builder/context.py
nat/builder/embedder.py
nat/builder/eval_builder.py
nat/builder/evaluator.py
nat/builder/framework_enum.py
nat/builder/front_end.py
nat/builder/function.py
nat/builder/function_base.py
nat/builder/function_info.py
nat/builder/intermediate_step_manager.py
nvidia_nat-1.3.1.dist-info/licenses/LICENSE-3rd-party.txt
nvidia_nat-1.3.1.dist-info/licenses/LICENSE.md
nvidia_nat-1.3.1.dist-info/METADATA
nvidia_nat-1.3.1.dist-info/WHEEL
nvidia_nat-1.3.1.dist-info/entry_points.txt
nvidia_nat-1.3.1.dist-info/top_level.txt
nvidia_nat-1.3.1.dist-info/RECORD
