Metadata-Version: 2.4
Name: nvidia-nat
Version: 1.3.1
Summary: NVIDIA NeMo Agent toolkit
Author: NVIDIA Corporation
Maintainer: NVIDIA Corporation
License: Apache-2.0
Project-URL: documentation, https://docs.nvidia.com/nemo/agent-toolkit/latest/
Project-URL: source, https://github.com/NVIDIA/NeMo-Agent-Toolkit
Keywords: ai,rag,agents
Classifier: Programming Language :: Python
Classifier: Programming Language :: Python :: 3.11
Classifier: Programming Language :: Python :: 3.12
Classifier: Programming Language :: Python :: 3.13
Requires-Python: <3.14,>=3.11
License-File: LICENSE-3rd-party.txt
License-File: LICENSE.md
Requires-Dist: aioboto3>=11.0.0
Requires-Dist: authlib<2.0.0,>=1.6.5
Requires-Dist: click~=8.1
Requires-Dist: colorama~=0.4.6
Requires-Dist: datasets~=4.0
Requires-Dist: expandvars~=1.0
Requires-Dist: fastapi~=0.115.5
Requires-Dist: httpx~=0.27
Requires-Dist: jinja2~=3.1
Requires-Dist: jsonpath-ng~=1.7
Requires-Dist: mcp~=1.13
Requires-Dist: nest-asyncio~=1.6
Requires-Dist: networkx~=3.4
Requires-Dist: numpy~=1.26; python_version < "3.12"
Requires-Dist: numpy~=2.3; python_version >= "3.12"
Requires-Dist: openinference-semantic-conventions~=0.1.14
Requires-Dist: openpyxl~=3.1
Requires-Dist: optuna~=4.4.0
Requires-Dist: pip>=24.3.1
Requires-Dist: pkce==1.0.3
Requires-Dist: pkginfo~=1.12
Requires-Dist: platformdirs~=4.3
Requires-Dist: pydantic~=2.11
Requires-Dist: pymilvus~=2.4
Requires-Dist: python-dotenv~=1.1.1
Requires-Dist: PyYAML~=6.0
Requires-Dist: ragas~=0.2.14
Requires-Dist: rich~=13.9
Requires-Dist: tabulate~=0.9
Requires-Dist: uvicorn[standard]<0.36
Requires-Dist: wikipedia~=1.4
Provides-Extra: all
Requires-Dist: nvidia-nat-all; extra == "all"
Provides-Extra: adk
Requires-Dist: nvidia-nat-adk; extra == "adk"
Provides-Extra: agno
Requires-Dist: nvidia-nat-agno; extra == "agno"
Provides-Extra: crewai
Requires-Dist: nvidia-nat-crewai; extra == "crewai"
Provides-Extra: data-flywheel
Requires-Dist: nvidia-nat-data-flywheel; extra == "data-flywheel"
Provides-Extra: ingestion
Requires-Dist: nvidia-nat-ingestion; extra == "ingestion"
Provides-Extra: langchain
Requires-Dist: nvidia-nat-langchain; extra == "langchain"
Provides-Extra: llama-index
Requires-Dist: nvidia-nat-llama-index; extra == "llama-index"
Provides-Extra: mcp
Requires-Dist: nvidia-nat-mcp; extra == "mcp"
Provides-Extra: mem0ai
Requires-Dist: nvidia-nat-mem0ai; extra == "mem0ai"
Provides-Extra: opentelemetry
Requires-Dist: nvidia-nat-opentelemetry; extra == "opentelemetry"
Provides-Extra: phoenix
Requires-Dist: nvidia-nat-phoenix; extra == "phoenix"
Provides-Extra: profiling
Requires-Dist: nvidia-nat-profiling; extra == "profiling"
Provides-Extra: ragaai
Requires-Dist: nvidia-nat-ragaai; extra == "ragaai"
Provides-Extra: mysql
Requires-Dist: nvidia-nat-mysql; extra == "mysql"
Provides-Extra: redis
Requires-Dist: nvidia-nat-redis; extra == "redis"
Provides-Extra: s3
Requires-Dist: nvidia-nat-s3; extra == "s3"
Provides-Extra: semantic-kernel
Requires-Dist: nvidia-nat-semantic-kernel; extra == "semantic-kernel"
Provides-Extra: telemetry
Requires-Dist: nvidia-nat-data-flywheel; extra == "telemetry"
Requires-Dist: nvidia-nat-opentelemetry; extra == "telemetry"
Requires-Dist: nvidia-nat-phoenix; extra == "telemetry"
Requires-Dist: nvidia-nat-ragaai; extra == "telemetry"
Requires-Dist: nvidia-nat-weave; extra == "telemetry"
Provides-Extra: test
Requires-Dist: nvidia-nat-test; extra == "test"
Provides-Extra: weave
Requires-Dist: nvidia-nat-weave; extra == "weave"
Provides-Extra: zep-cloud
Requires-Dist: nvidia-nat-zep-cloud; extra == "zep-cloud"
Provides-Extra: examples
Requires-Dist: nat_adk_demo; extra == "examples"
Requires-Dist: nat_agno_personal_finance; extra == "examples"
Requires-Dist: nat_haystack_deep_research_agent; extra == "examples"
Requires-Dist: nat_alert_triage_agent; extra == "examples"
Requires-Dist: nat_automated_description_generation; extra == "examples"
Requires-Dist: nat_email_phishing_analyzer; extra == "examples"
Requires-Dist: nat_multi_frameworks; extra == "examples"
Requires-Dist: nat_plot_charts; extra == "examples"
Requires-Dist: nat_por_to_jiratickets; extra == "examples"
Requires-Dist: nat_profiler_agent; extra == "examples"
Requires-Dist: nat_router_agent; extra == "examples"
Requires-Dist: nat_semantic_kernel_demo; extra == "examples"
Requires-Dist: nat_sequential_executor; extra == "examples"
Requires-Dist: nat_simple_auth; extra == "examples"
Requires-Dist: nat_simple_auth_mcp; extra == "examples"
Requires-Dist: nat_simple_web_query; extra == "examples"
Requires-Dist: nat_simple_web_query_eval; extra == "examples"
Requires-Dist: nat_simple_calculator; extra == "examples"
Requires-Dist: nat_simple_calculator_custom_routes; extra == "examples"
Requires-Dist: nat_simple_calculator_eval; extra == "examples"
Requires-Dist: nat_simple_calculator_mcp; extra == "examples"
Requires-Dist: nat_simple_calculator_observability; extra == "examples"
Requires-Dist: nat_simple_calculator_hitl; extra == "examples"
Requires-Dist: nat_simple_rag; extra == "examples"
Requires-Dist: nat_swe_bench; extra == "examples"
Requires-Dist: nat_user_report; extra == "examples"
Provides-Extra: gunicorn
Requires-Dist: gunicorn~=23.0; extra == "gunicorn"
Provides-Extra: async-endpoints
Requires-Dist: aiosqlite~=0.21; extra == "async-endpoints"
Requires-Dist: dask==2023.6; extra == "async-endpoints"
Requires-Dist: distributed==2023.6; extra == "async-endpoints"
Requires-Dist: sqlalchemy[asyncio]~=2.0; extra == "async-endpoints"
Provides-Extra: nvidia-haystack
Requires-Dist: nvidia-haystack~=0.3.0; extra == "nvidia-haystack"
Provides-Extra: litellm
Requires-Dist: litellm==1.74.9; extra == "litellm"
Provides-Extra: openai
Requires-Dist: openai~=1.106; extra == "openai"
Dynamic: license-file
